{
  "date": "2026-06-09",
  "updated": "2026-06-09 10:07 UTC",
  "source": "TWSE(breakdown)+FinMind(sit)+FinMind(dealer)",
  "unit": "千股",
  "summary": {
    "fi": -110520,
    "sit": -25482,
    "dealer": 181179,
    "total": 45177
  },
  "fi": {
    "top": [
      {
        "code": "2892",
        "name": "第一金",
        "fi": 64068,
        "sit": 0,
        "dealer": 0,
        "total": 64068
      },
      {
        "code": "2801",
        "name": "彰銀",
        "fi": 61779,
        "sit": 0,
        "dealer": 0,
        "total": 61779
      },
      {
        "code": "2887",
        "name": "台新新光金",
        "fi": 44816,
        "sit": 0,
        "dealer": 0,
        "total": 44816
      },
      {
        "code": "2834",
        "name": "臺企銀",
        "fi": 40676,
        "sit": 0,
        "dealer": 0,
        "total": 40676
      },
      {
        "code": "2884",
        "name": "玉山金",
        "fi": 39677,
        "sit": 0,
        "dealer": 0,
        "total": 39677
      },
      {
        "code": "00403A",
        "name": "主動統一升級50",
        "fi": 36865,
        "sit": 0,
        "dealer": 153292,
        "total": 190157
      },
      {
        "code": "2890",
        "name": "永豐金",
        "fi": 36082,
        "sit": 0,
        "dealer": 0,
        "total": 36082
      },
      {
        "code": "00981A",
        "name": "主動統一台股增長",
        "fi": 35489,
        "sit": 17410,
        "dealer": 1917,
        "total": 54816
      },
      {
        "code": "2867",
        "name": "三商壽",
        "fi": 26148,
        "sit": 0,
        "dealer": 0,
        "total": 26148
      },
      {
        "code": "5880",
        "name": "合庫金",
        "fi": 22222,
        "sit": 0,
        "dealer": 0,
        "total": 22222
      }
    ],
    "bot": [
      {
        "code": "2409",
        "name": "友達",
        "fi": -80413,
        "sit": 0,
        "dealer": 0,
        "total": -80413
      },
      {
        "code": "2883",
        "name": "凱基金",
        "fi": -80409,
        "sit": 0,
        "dealer": 0,
        "total": -80409
      },
      {
        "code": "2344",
        "name": "華邦電",
        "fi": -48095,
        "sit": 0,
        "dealer": 0,
        "total": -48095
      },
      {
        "code": "2324",
        "name": "仁寶",
        "fi": -39354,
        "sit": 0,
        "dealer": 0,
        "total": -39354
      },
      {
        "code": "0050",
        "name": "元大台灣50",
        "fi": -21647,
        "sit": 2450,
        "dealer": -13469,
        "total": -32666
      },
      {
        "code": "2002",
        "name": "中鋼",
        "fi": -18019,
        "sit": 0,
        "dealer": 0,
        "total": -18019
      },
      {
        "code": "2881",
        "name": "富邦金",
        "fi": -17485,
        "sit": 24527,
        "dealer": -382,
        "total": 6660
      },
      {
        "code": "00919",
        "name": "群益台灣精選高息",
        "fi": -16234,
        "sit": 0,
        "dealer": 9411,
        "total": -6823
      },
      {
        "code": "1402",
        "name": "遠東新",
        "fi": -16106,
        "sit": 0,
        "dealer": 0,
        "total": -16106
      },
      {
        "code": "00712",
        "name": "復華富時不動產",
        "fi": -15726,
        "sit": 0,
        "dealer": 0,
        "total": -15726
      }
    ]
  },
  "sit": {
    "top": [
      {
        "code": "2881",
        "name": "富邦金",
        "fi": -17485,
        "sit": 24527,
        "dealer": -382,
        "total": 6660
      },
      {
        "code": "00981A",
        "name": "主動統一台股增長",
        "fi": 35489,
        "sit": 17410,
        "dealer": 1917,
        "total": 54816
      },
      {
        "code": "2382",
        "name": "廣達",
        "fi": -12263,
        "sit": 9612,
        "dealer": -285,
        "total": -2936
      },
      {
        "code": "2330",
        "name": "台積電",
        "fi": -15009,
        "sit": 2670,
        "dealer": -1254,
        "total": -13593
      },
      {
        "code": "0050",
        "name": "元大台灣50",
        "fi": -21647,
        "sit": 2450,
        "dealer": -13469,
        "total": -32666
      },
      {
        "code": "2376",
        "name": "技嘉",
        "fi": -2934,
        "sit": 893,
        "dealer": 112,
        "total": -1929
      },
      {
        "code": "8046",
        "name": "南電",
        "fi": 1529,
        "sit": 839,
        "dealer": 255,
        "total": 2623
      },
      {
        "code": "2308",
        "name": "台達電",
        "fi": 438,
        "sit": 787,
        "dealer": 451,
        "total": 1676
      },
      {
        "code": "2454",
        "name": "聯發科",
        "fi": -1210,
        "sit": 637,
        "dealer": -163,
        "total": -736
      },
      {
        "code": "3231",
        "name": "緯創",
        "fi": -15505,
        "sit": 553,
        "dealer": -804,
        "total": -15756
      }
    ],
    "bot": [
      {
        "code": "2303",
        "name": "聯電",
        "fi": 2006,
        "sit": -67388,
        "dealer": 8334,
        "total": -57048
      },
      {
        "code": "2891",
        "name": "中信金",
        "fi": 5891,
        "sit": -10158,
        "dealer": 1384,
        "total": -2883
      },
      {
        "code": "2603",
        "name": "長榮",
        "fi": -1620,
        "sit": -4250,
        "dealer": -57,
        "total": -5927
      },
      {
        "code": "1802",
        "name": "台玻",
        "fi": -6800,
        "sit": -3600,
        "dealer": -743,
        "total": -11143
      },
      {
        "code": "2882",
        "name": "國泰金",
        "fi": 4854,
        "sit": -653,
        "dealer": 730,
        "total": 4931
      },
      {
        "code": "3189",
        "name": "景碩",
        "fi": 640,
        "sit": -356,
        "dealer": -305,
        "total": -21
      },
      {
        "code": "2356",
        "name": "英業達",
        "fi": -11118,
        "sit": -76,
        "dealer": -164,
        "total": -11358
      },
      {
        "code": "3711",
        "name": "日月光投控",
        "fi": -5558,
        "sit": -25,
        "dealer": -77,
        "total": -5660
      },
      {
        "code": "6669",
        "name": "緯穎",
        "fi": -238,
        "sit": -2,
        "dealer": -4,
        "total": -244
      }
    ]
  },
  "dealer": {
    "top": [
      {
        "code": "00403A",
        "name": "主動統一升級50",
        "fi": 36865,
        "sit": 0,
        "dealer": 153292,
        "total": 190157
      },
      {
        "code": "00878",
        "name": "國泰永續高股息",
        "fi": -1506,
        "sit": 0,
        "dealer": 33850,
        "total": 32344
      },
      {
        "code": "00940",
        "name": "元大台灣價值高息",
        "fi": 774,
        "sit": 0,
        "dealer": 12602,
        "total": 13376
      },
      {
        "code": "00919",
        "name": "群益台灣精選高息",
        "fi": -16234,
        "sit": 0,
        "dealer": 9411,
        "total": -6823
      },
      {
        "code": "2303",
        "name": "聯電",
        "fi": 2006,
        "sit": -67388,
        "dealer": 8334,
        "total": -57048
      },
      {
        "code": "00980A",
        "name": "主動野村臺灣優選",
        "fi": -3344,
        "sit": 0,
        "dealer": 7167,
        "total": 3823
      },
      {
        "code": "00981A",
        "name": "主動統一台股增長",
        "fi": 35489,
        "sit": 17410,
        "dealer": 1917,
        "total": 54816
      },
      {
        "code": "00663L",
        "name": "國泰臺灣加權正2",
        "fi": 724,
        "sit": 0,
        "dealer": 1677,
        "total": 2401
      },
      {
        "code": "2891",
        "name": "中信金",
        "fi": 5891,
        "sit": -10158,
        "dealer": 1384,
        "total": -2883
      },
      {
        "code": "2882",
        "name": "國泰金",
        "fi": 4854,
        "sit": -653,
        "dealer": 730,
        "total": 4931
      }
    ],
    "bot": [
      {
        "code": "00988A",
        "name": "主動統一全球創新",
        "fi": 3126,
        "sit": 0,
        "dealer": -14003,
        "total": -10877
      },
      {
        "code": "0050",
        "name": "元大台灣50",
        "fi": -21647,
        "sit": 2450,
        "dealer": -13469,
        "total": -32666
      },
      {
        "code": "00631L",
        "name": "元大台灣50正2",
        "fi": 14396,
        "sit": 0,
        "dealer": -10866,
        "total": 3530
      },
      {
        "code": "00929",
        "name": "復華台灣科技優息",
        "fi": 3923,
        "sit": 0,
        "dealer": -4181,
        "total": -258
      },
      {
        "code": "00935",
        "name": "野村臺灣新科技50",
        "fi": -122,
        "sit": 180,
        "dealer": -2868,
        "total": -2810
      },
      {
        "code": "2330",
        "name": "台積電",
        "fi": -15009,
        "sit": 2670,
        "dealer": -1254,
        "total": -13593
      },
      {
        "code": "6770",
        "name": "力積電",
        "fi": -3219,
        "sit": 0,
        "dealer": -1052,
        "total": -4271
      },
      {
        "code": "3231",
        "name": "緯創",
        "fi": -15505,
        "sit": 553,
        "dealer": -804,
        "total": -15756
      },
      {
        "code": "1802",
        "name": "台玻",
        "fi": -6800,
        "sit": -3600,
        "dealer": -743,
        "total": -11143
      },
      {
        "code": "2881",
        "name": "富邦金",
        "fi": -17485,
        "sit": 24527,
        "dealer": -382,
        "total": 6660
      }
    ]
  },
  "total": {
    "top": [
      {
        "code": "00403A",
        "name": "主動統一升級50",
        "fi": 36865,
        "sit": 0,
        "dealer": 153292,
        "total": 190157
      },
      {
        "code": "2892",
        "name": "第一金",
        "fi": 64068,
        "sit": 0,
        "dealer": 0,
        "total": 64068
      },
      {
        "code": "2801",
        "name": "彰銀",
        "fi": 61779,
        "sit": 0,
        "dealer": 0,
        "total": 61779
      },
      {
        "code": "00981A",
        "name": "主動統一台股增長",
        "fi": 35489,
        "sit": 17410,
        "dealer": 1917,
        "total": 54816
      },
      {
        "code": "2887",
        "name": "台新新光金",
        "fi": 44816,
        "sit": 0,
        "dealer": 0,
        "total": 44816
      },
      {
        "code": "2834",
        "name": "臺企銀",
        "fi": 40676,
        "sit": 0,
        "dealer": 0,
        "total": 40676
      },
      {
        "code": "2884",
        "name": "玉山金",
        "fi": 39677,
        "sit": 0,
        "dealer": 0,
        "total": 39677
      },
      {
        "code": "2890",
        "name": "永豐金",
        "fi": 36082,
        "sit": 0,
        "dealer": 0,
        "total": 36082
      },
      {
        "code": "00878",
        "name": "國泰永續高股息",
        "fi": -1506,
        "sit": 0,
        "dealer": 33850,
        "total": 32344
      },
      {
        "code": "2867",
        "name": "三商壽",
        "fi": 26148,
        "sit": 0,
        "dealer": 0,
        "total": 26148
      }
    ],
    "bot": [
      {
        "code": "2409",
        "name": "友達",
        "fi": -80413,
        "sit": 0,
        "dealer": 0,
        "total": -80413
      },
      {
        "code": "2883",
        "name": "凱基金",
        "fi": -80409,
        "sit": 0,
        "dealer": 0,
        "total": -80409
      },
      {
        "code": "2303",
        "name": "聯電",
        "fi": 2006,
        "sit": -67388,
        "dealer": 8334,
        "total": -57048
      },
      {
        "code": "2344",
        "name": "華邦電",
        "fi": -48095,
        "sit": 0,
        "dealer": 0,
        "total": -48095
      },
      {
        "code": "2324",
        "name": "仁寶",
        "fi": -39354,
        "sit": 0,
        "dealer": 0,
        "total": -39354
      },
      {
        "code": "0050",
        "name": "元大台灣50",
        "fi": -21647,
        "sit": 2450,
        "dealer": -13469,
        "total": -32666
      },
      {
        "code": "2002",
        "name": "中鋼",
        "fi": -18019,
        "sit": 0,
        "dealer": 0,
        "total": -18019
      },
      {
        "code": "1402",
        "name": "遠東新",
        "fi": -16106,
        "sit": 0,
        "dealer": 0,
        "total": -16106
      },
      {
        "code": "3231",
        "name": "緯創",
        "fi": -15505,
        "sit": 553,
        "dealer": -804,
        "total": -15756
      },
      {
        "code": "00712",
        "name": "復華富時不動產",
        "fi": -15726,
        "sit": 0,
        "dealer": 0,
        "total": -15726
      }
    ]
  },
  "etf": {
    "top": [
      {
        "code": "00403A",
        "name": "主動統一升級50",
        "fi": 36865,
        "sit": 0,
        "dealer": 153292,
        "total": 190157
      },
      {
        "code": "00981A",
        "name": "主動統一台股增長",
        "fi": 35489,
        "sit": 17410,
        "dealer": 1917,
        "total": 54816
      },
      {
        "code": "00878",
        "name": "國泰永續高股息",
        "fi": -1506,
        "sit": 0,
        "dealer": 33850,
        "total": 32344
      },
      {
        "code": "00991A",
        "name": "主動復華未來50",
        "fi": 17291,
        "sit": 0,
        "dealer": 0,
        "total": 17291
      },
      {
        "code": "00940",
        "name": "元大台灣價值高息",
        "fi": 774,
        "sit": 0,
        "dealer": 12602,
        "total": 13376
      },
      {
        "code": "00992A",
        "name": "主動群益科技創新",
        "fi": 12726,
        "sit": 0,
        "dealer": 0,
        "total": 12726
      },
      {
        "code": "00400A",
        "name": "主動國泰動能高息",
        "fi": 7103,
        "sit": 0,
        "dealer": 0,
        "total": 7103
      },
      {
        "code": "0056",
        "name": "元大高股息",
        "fi": 4955,
        "sit": 0,
        "dealer": 0,
        "total": 4955
      },
      {
        "code": "00990A",
        "name": "主動元大AI新經濟",
        "fi": 4838,
        "sit": 0,
        "dealer": 0,
        "total": 4838
      },
      {
        "code": "00980A",
        "name": "主動野村臺灣優選",
        "fi": -3344,
        "sit": 0,
        "dealer": 7167,
        "total": 3823
      },
      {
        "code": "00631L",
        "name": "元大台灣50正2",
        "fi": 14396,
        "sit": 0,
        "dealer": -10866,
        "total": 3530
      },
      {
        "code": "00997A",
        "name": "主動群益美國增長",
        "fi": 3327,
        "sit": 0,
        "dealer": 0,
        "total": 3327
      },
      {
        "code": "00939",
        "name": "統一台灣高息動能",
        "fi": 2664,
        "sit": 0,
        "dealer": 0,
        "total": 2664
      },
      {
        "code": "00993A",
        "name": "主動安聯台灣",
        "fi": 2531,
        "sit": 0,
        "dealer": 0,
        "total": 2531
      },
      {
        "code": "00663L",
        "name": "國泰臺灣加權正2",
        "fi": 724,
        "sit": 0,
        "dealer": 1677,
        "total": 2401
      }
    ],
    "bot": [
      {
        "code": "0050",
        "name": "元大台灣50",
        "fi": -21647,
        "sit": 2450,
        "dealer": -13469,
        "total": -32666
      },
      {
        "code": "00712",
        "name": "復華富時不動產",
        "fi": -15726,
        "sit": 0,
        "dealer": 0,
        "total": -15726
      },
      {
        "code": "00953B",
        "name": "群益優選非投等債",
        "fi": -13197,
        "sit": 0,
        "dealer": 0,
        "total": -13197
      },
      {
        "code": "00988A",
        "name": "主動統一全球創新",
        "fi": 3126,
        "sit": 0,
        "dealer": -14003,
        "total": -10877
      },
      {
        "code": "00999A",
        "name": "主動野村臺灣高息",
        "fi": -9443,
        "sit": 0,
        "dealer": 0,
        "total": -9443
      },
      {
        "code": "009816",
        "name": "凱基台灣TOP50",
        "fi": -7932,
        "sit": 0,
        "dealer": 0,
        "total": -7932
      },
      {
        "code": "00919",
        "name": "群益台灣精選高息",
        "fi": -16234,
        "sit": 0,
        "dealer": 9411,
        "total": -6823
      },
      {
        "code": "00985B",
        "name": "群益ESG投等債0-5",
        "fi": -5028,
        "sit": 0,
        "dealer": 0,
        "total": -5028
      },
      {
        "code": "009820",
        "name": "元大納斯達克精選",
        "fi": -4196,
        "sit": 0,
        "dealer": 0,
        "total": -4196
      },
      {
        "code": "00935",
        "name": "野村臺灣新科技50",
        "fi": -122,
        "sit": 180,
        "dealer": -2868,
        "total": -2810
      },
      {
        "code": "00947",
        "name": "台新臺灣IC設計",
        "fi": -2308,
        "sit": 0,
        "dealer": 0,
        "total": -2308
      },
      {
        "code": "0052",
        "name": "富邦科技",
        "fi": -2133,
        "sit": 0,
        "dealer": 0,
        "total": -2133
      },
      {
        "code": "00662",
        "name": "富邦NASDAQ",
        "fi": -1699,
        "sit": 0,
        "dealer": 0,
        "total": -1699
      },
      {
        "code": "00865B",
        "name": "國泰US短期公債",
        "fi": -1642,
        "sit": 0,
        "dealer": 0,
        "total": -1642
      },
      {
        "code": "00927",
        "name": "群益半導體收益",
        "fi": -1617,
        "sit": 0,
        "dealer": 0,
        "total": -1617
      }
    ]
  },
  "history": [
    {
      "date": "2026-05-15",
      "fi_b": [
        [
          "3481",
          "群創",
          91015
        ],
        [
          "2881",
          "富邦金",
          60621
        ],
        [
          "2317",
          "鴻海",
          59174
        ],
        [
          "6770",
          "力積電",
          56009
        ],
        [
          "2887",
          "台新新光金",
          47700
        ],
        [
          "009820",
          "元大納斯達克精選",
          37316
        ],
        [
          "2882",
          "國泰金",
          29280
        ],
        [
          "2027",
          "大成鋼",
          23026
        ],
        [
          "2344",
          "華邦電",
          16049
        ],
        [
          "6239",
          "力成",
          15569
        ]
      ],
      "fi_s": [
        [
          "00403A",
          "主動統一升級50",
          -403620
        ],
        [
          "00981A",
          "主動統一台股增長",
          -67700
        ],
        [
          "2324",
          "仁寶",
          -63723
        ],
        [
          "00878",
          "國泰永續高股息",
          -32225
        ],
        [
          "00991A",
          "主動復華未來50",
          -29475
        ],
        [
          "2382",
          "廣達",
          -27152
        ],
        [
          "00992A",
          "主動群益科技創新",
          -25390
        ],
        [
          "0050",
          "元大台灣50",
          -24068
        ],
        [
          "2408",
          "南亞科",
          -23728
        ],
        [
          "2801",
          "彰銀",
          -22865
        ]
      ],
      "sit_b": [],
      "sit_s": []
    },
    {
      "date": "2026-05-18",
      "fi_b": [
        [
          "00953B",
          "群益優選非投等債",
          19501
        ],
        [
          "00400A",
          "主動國泰動能高息",
          13371
        ],
        [
          "2313",
          "華通",
          13246
        ],
        [
          "00990A",
          "主動元大AI新經濟",
          12995
        ],
        [
          "00997A",
          "主動群益美國增長",
          11087
        ],
        [
          "009820",
          "元大納斯達克精選",
          10607
        ],
        [
          "00992A",
          "主動群益科技創新",
          10328
        ],
        [
          "2355",
          "敬鵬",
          10321
        ],
        [
          "2485",
          "兆赫",
          8088
        ],
        [
          "00991A",
          "主動復華未來50",
          8002
        ]
      ],
      "fi_s": [
        [
          "00403A",
          "主動統一升級50",
          -85867
        ],
        [
          "2303",
          "聯電",
          -45922
        ],
        [
          "0050",
          "元大台灣50",
          -43214
        ],
        [
          "2883",
          "凱基金",
          -27860
        ],
        [
          "3481",
          "群創",
          -26509
        ],
        [
          "00878",
          "國泰永續高股息",
          -19298
        ],
        [
          "2344",
          "華邦電",
          -19139
        ],
        [
          "6770",
          "力積電",
          -18227
        ],
        [
          "1101",
          "台泥",
          -17030
        ],
        [
          "2887",
          "台新新光金",
          -12897
        ]
      ],
      "sit_b": [],
      "sit_s": []
    },
    {
      "date": "2026-05-19",
      "fi_b": [
        [
          "2887",
          "台新新光金",
          32409
        ],
        [
          "2890",
          "永豐金",
          30861
        ],
        [
          "2891",
          "中信金",
          30684
        ],
        [
          "2882",
          "國泰金",
          25404
        ],
        [
          "2886",
          "兆豐金",
          21977
        ],
        [
          "2412",
          "中華電",
          16215
        ],
        [
          "2881",
          "富邦金",
          14429
        ],
        [
          "2880",
          "華南金",
          13565
        ],
        [
          "3045",
          "台灣大",
          13020
        ],
        [
          "2883",
          "凱基金",
          12795
        ]
      ],
      "fi_s": [
        [
          "00403A",
          "主動統一升級50",
          -66234
        ],
        [
          "00981A",
          "主動統一台股增長",
          -60602
        ],
        [
          "2344",
          "華邦電",
          -48979
        ],
        [
          "2337",
          "旺宏",
          -47411
        ],
        [
          "0050",
          "元大台灣50",
          -46447
        ],
        [
          "3481",
          "群創",
          -44963
        ],
        [
          "6770",
          "力積電",
          -31837
        ],
        [
          "00990A",
          "主動元大AI新經濟",
          -21118
        ],
        [
          "2408",
          "南亞科",
          -20376
        ],
        [
          "2330",
          "台積電",
          -17247
        ]
      ],
      "sit_b": [
        [
          "2303",
          "聯電",
          32256
        ],
        [
          "2330",
          "台積電",
          4144
        ],
        [
          "3008",
          "大立光",
          249
        ],
        [
          "0050",
          "元大台灣50",
          246
        ],
        [
          "00935",
          "野村臺灣新科技50",
          158
        ],
        [
          "3711",
          "日月光投控",
          17
        ],
        [
          "6770",
          "力積電",
          5
        ],
        [
          "4961",
          "天鈺",
          1
        ]
      ],
      "sit_s": [
        [
          "2882",
          "國泰金",
          -17967
        ],
        [
          "2891",
          "中信金",
          -15649
        ],
        [
          "2603",
          "長榮",
          -4217
        ],
        [
          "2881",
          "富邦金",
          -2842
        ],
        [
          "2308",
          "台達電",
          -1167
        ],
        [
          "2382",
          "廣達",
          -1060
        ],
        [
          "2454",
          "聯發科",
          -490
        ]
      ]
    },
    {
      "date": "2026-05-20",
      "fi_b": [
        [
          "2891",
          "中信金",
          50583
        ],
        [
          "2887",
          "台新新光金",
          36307
        ],
        [
          "2603",
          "長榮",
          25570
        ],
        [
          "2027",
          "大成鋼",
          21268
        ],
        [
          "2337",
          "旺宏",
          13039
        ],
        [
          "3481",
          "群創",
          12966
        ],
        [
          "2344",
          "華邦電",
          12724
        ],
        [
          "00982A",
          "主動群益台灣強棒",
          11159
        ],
        [
          "2883",
          "凱基金",
          10461
        ],
        [
          "00988A",
          "主動統一全球創新",
          10364
        ]
      ],
      "fi_s": [
        [
          "2892",
          "第一金",
          -136974
        ],
        [
          "00403A",
          "主動統一升級50",
          -56611
        ],
        [
          "2303",
          "聯電",
          -55126
        ],
        [
          "2409",
          "友達",
          -16817
        ],
        [
          "00981A",
          "主動統一台股增長",
          -15822
        ],
        [
          "0050",
          "元大台灣50",
          -15132
        ],
        [
          "2884",
          "玉山金",
          -14234
        ],
        [
          "9904",
          "寶成",
          -13670
        ],
        [
          "2317",
          "鴻海",
          -12760
        ],
        [
          "1802",
          "台玻",
          -11888
        ]
      ],
      "sit_b": [
        [
          "2303",
          "聯電",
          18274
        ],
        [
          "2330",
          "台積電",
          2188
        ],
        [
          "0050",
          "元大台灣50",
          885
        ],
        [
          "3711",
          "日月光投控",
          688
        ],
        [
          "6770",
          "力積電",
          565
        ],
        [
          "2881",
          "富邦金",
          223
        ],
        [
          "00935",
          "野村臺灣新科技50",
          123
        ],
        [
          "3008",
          "大立光",
          120
        ]
      ],
      "sit_s": [
        [
          "2891",
          "中信金",
          -3889
        ],
        [
          "2603",
          "長榮",
          -2441
        ],
        [
          "2382",
          "廣達",
          -1984
        ],
        [
          "00981A",
          "主動統一台股增長",
          -1255
        ],
        [
          "2308",
          "台達電",
          -1010
        ],
        [
          "2882",
          "國泰金",
          -955
        ],
        [
          "2454",
          "聯發科",
          -61
        ],
        [
          "2634",
          "漢翔",
          -4
        ],
        [
          "1802",
          "台玻",
          -1
        ]
      ]
    },
    {
      "date": "2026-05-21",
      "fi_b": [
        [
          "2409",
          "友達",
          156969
        ],
        [
          "3481",
          "群創",
          98088
        ],
        [
          "2324",
          "仁寶",
          52078
        ],
        [
          "2312",
          "金寶",
          46559
        ],
        [
          "2303",
          "聯電",
          43788
        ],
        [
          "00878",
          "國泰永續高股息",
          35847
        ],
        [
          "1303",
          "南亞",
          32941
        ],
        [
          "6116",
          "彩晶",
          31811
        ],
        [
          "2891",
          "中信金",
          28023
        ],
        [
          "3231",
          "緯創",
          27614
        ]
      ],
      "fi_s": [
        [
          "2892",
          "第一金",
          -71795
        ],
        [
          "2887",
          "台新新光金",
          -34822
        ],
        [
          "2344",
          "華邦電",
          -31197
        ],
        [
          "2883",
          "凱基金",
          -24683
        ],
        [
          "2337",
          "旺宏",
          -22873
        ],
        [
          "2884",
          "玉山金",
          -11670
        ],
        [
          "2002",
          "中鋼",
          -10626
        ],
        [
          "2481",
          "強茂",
          -9062
        ],
        [
          "1101",
          "台泥",
          -8004
        ],
        [
          "2801",
          "彰銀",
          -7316
        ]
      ],
      "sit_b": [
        [
          "2382",
          "廣達",
          9439
        ],
        [
          "0050",
          "元大台灣50",
          3770
        ],
        [
          "2603",
          "長榮",
          986
        ],
        [
          "2330",
          "台積電",
          167
        ],
        [
          "3008",
          "大立光",
          24
        ],
        [
          "1802",
          "台玻",
          22
        ],
        [
          "4961",
          "天鈺",
          4
        ]
      ],
      "sit_s": [
        [
          "2303",
          "聯電",
          -25960
        ],
        [
          "2891",
          "中信金",
          -22482
        ],
        [
          "2882",
          "國泰金",
          -21948
        ],
        [
          "2881",
          "富邦金",
          -14009
        ],
        [
          "2454",
          "聯發科",
          -400
        ],
        [
          "2308",
          "台達電",
          -254
        ],
        [
          "3711",
          "日月光投控",
          -23
        ],
        [
          "2634",
          "漢翔",
          -7
        ]
      ]
    },
    {
      "date": "2026-05-22",
      "fi_b": [
        [
          "00403A",
          "主動統一升級50",
          130828
        ],
        [
          "00981A",
          "主動統一台股增長",
          98462
        ],
        [
          "6770",
          "力積電",
          96770
        ],
        [
          "2344",
          "華邦電",
          51442
        ],
        [
          "00878",
          "國泰永續高股息",
          45650
        ],
        [
          "1802",
          "台玻",
          36032
        ],
        [
          "3231",
          "緯創",
          32967
        ],
        [
          "00992A",
          "主動群益科技創新",
          29170
        ],
        [
          "2313",
          "華通",
          29085
        ],
        [
          "2409",
          "友達",
          28252
        ]
      ],
      "fi_s": [
        [
          "2892",
          "第一金",
          -69440
        ],
        [
          "2303",
          "聯電",
          -30347
        ],
        [
          "2887",
          "台新新光金",
          -28740
        ],
        [
          "2890",
          "永豐金",
          -21853
        ],
        [
          "8150",
          "南茂",
          -17100
        ],
        [
          "2002",
          "中鋼",
          -14673
        ],
        [
          "1303",
          "南亞",
          -13198
        ],
        [
          "2880",
          "華南金",
          -12353
        ],
        [
          "1216",
          "統一",
          -12080
        ],
        [
          "2610",
          "華航",
          -12053
        ]
      ],
      "sit_b": [
        [
          "2382",
          "廣達",
          12275
        ],
        [
          "00988A",
          "主動統一全球創新",
          7600
        ],
        [
          "2603",
          "長榮",
          5065
        ],
        [
          "2454",
          "聯發科",
          1549
        ],
        [
          "3711",
          "日月光投控",
          1251
        ],
        [
          "6770",
          "力積電",
          588
        ],
        [
          "0050",
          "元大台灣50",
          85
        ],
        [
          "1802",
          "台玻",
          11
        ],
        [
          "3008",
          "大立光",
          2
        ]
      ],
      "sit_s": [
        [
          "2303",
          "聯電",
          -24879
        ],
        [
          "2882",
          "國泰金",
          -22122
        ],
        [
          "2881",
          "富邦金",
          -16206
        ],
        [
          "2891",
          "中信金",
          -2066
        ],
        [
          "2330",
          "台積電",
          -432
        ],
        [
          "2308",
          "台達電",
          -109
        ],
        [
          "4961",
          "天鈺",
          -1
        ]
      ]
    },
    {
      "date": "2026-05-25",
      "fi_b": [
        [
          "00403A",
          "主動統一升級50",
          92888
        ],
        [
          "00878",
          "國泰永續高股息",
          75375
        ],
        [
          "2344",
          "華邦電",
          72092
        ],
        [
          "6770",
          "力積電",
          70137
        ],
        [
          "2324",
          "仁寶",
          57814
        ],
        [
          "2317",
          "鴻海",
          52052
        ],
        [
          "2303",
          "聯電",
          48519
        ],
        [
          "1802",
          "台玻",
          43212
        ],
        [
          "00919",
          "群益台灣精選高息",
          31796
        ],
        [
          "00982A",
          "主動群益台灣強棒",
          31703
        ]
      ],
      "fi_s": [
        [
          "2887",
          "台新新光金",
          -51064
        ],
        [
          "2892",
          "第一金",
          -46852
        ],
        [
          "2880",
          "華南金",
          -26169
        ],
        [
          "2382",
          "廣達",
          -19828
        ],
        [
          "2883",
          "凱基金",
          -19479
        ],
        [
          "3714",
          "富采",
          -18952
        ],
        [
          "1102",
          "亞泥",
          -18190
        ],
        [
          "2801",
          "彰銀",
          -18039
        ],
        [
          "00990A",
          "主動元大AI新經濟",
          -17820
        ],
        [
          "2884",
          "玉山金",
          -17644
        ]
      ],
      "sit_b": [
        [
          "2382",
          "廣達",
          10192
        ],
        [
          "2330",
          "台積電",
          4128
        ],
        [
          "2603",
          "長榮",
          3859
        ],
        [
          "00878",
          "國泰永續高股息",
          2500
        ],
        [
          "0050",
          "元大台灣50",
          1866
        ],
        [
          "3711",
          "日月光投控",
          1131
        ],
        [
          "00981A",
          "主動統一台股增長",
          220
        ],
        [
          "2308",
          "台達電",
          203
        ],
        [
          "00935",
          "野村臺灣新科技50",
          141
        ],
        [
          "00988A",
          "主動統一全球創新",
          120
        ]
      ],
      "sit_s": [
        [
          "2303",
          "聯電",
          -21406
        ],
        [
          "2882",
          "國泰金",
          -15598
        ],
        [
          "2881",
          "富邦金",
          -12757
        ],
        [
          "2891",
          "中信金",
          -5718
        ],
        [
          "2454",
          "聯發科",
          -961
        ],
        [
          "4961",
          "天鈺",
          -1
        ]
      ]
    },
    {
      "date": "2026-05-26",
      "fi_b": [
        [
          "2303",
          "聯電",
          71870
        ],
        [
          "6770",
          "力積電",
          59832
        ],
        [
          "2881",
          "富邦金",
          58964
        ],
        [
          "00403A",
          "主動統一升級50",
          50954
        ],
        [
          "2344",
          "華邦電",
          46872
        ],
        [
          "1303",
          "南亞",
          34097
        ],
        [
          "2312",
          "金寶",
          30455
        ],
        [
          "2337",
          "旺宏",
          29338
        ],
        [
          "2449",
          "京元電子",
          24629
        ],
        [
          "2882",
          "國泰金",
          23552
        ]
      ],
      "fi_s": [
        [
          "3481",
          "群創",
          -202890
        ],
        [
          "2409",
          "友達",
          -166130
        ],
        [
          "6116",
          "彩晶",
          -34300
        ],
        [
          "00981A",
          "主動統一台股增長",
          -32901
        ],
        [
          "2880",
          "華南金",
          -31854
        ],
        [
          "2356",
          "英業達",
          -31656
        ],
        [
          "2002",
          "中鋼",
          -25413
        ],
        [
          "2618",
          "長榮航",
          -24051
        ],
        [
          "2610",
          "華航",
          -17687
        ],
        [
          "00940",
          "元大台灣價值高息",
          -17033
        ]
      ],
      "sit_b": [
        [
          "2382",
          "廣達",
          12747
        ],
        [
          "00981A",
          "主動統一台股增長",
          12600
        ],
        [
          "2603",
          "長榮",
          7531
        ],
        [
          "2891",
          "中信金",
          4247
        ],
        [
          "0050",
          "元大台灣50",
          2131
        ],
        [
          "1802",
          "台玻",
          762
        ],
        [
          "00935",
          "野村臺灣新科技50",
          400
        ],
        [
          "6770",
          "力積電",
          302
        ],
        [
          "2308",
          "台達電",
          160
        ]
      ],
      "sit_s": [
        [
          "2303",
          "聯電",
          -19693
        ],
        [
          "2882",
          "國泰金",
          -17890
        ],
        [
          "2881",
          "富邦金",
          -15280
        ],
        [
          "2454",
          "聯發科",
          -599
        ],
        [
          "2330",
          "台積電",
          -598
        ],
        [
          "3711",
          "日月光投控",
          -43
        ],
        [
          "3008",
          "大立光",
          -13
        ],
        [
          "2634",
          "漢翔",
          -7
        ]
      ]
    },
    {
      "date": "2026-05-27",
      "fi_b": [
        [
          "00403A",
          "主動統一升級50",
          88667
        ],
        [
          "6770",
          "力積電",
          74224
        ],
        [
          "00919",
          "群益台灣精選高息",
          53577
        ],
        [
          "00878",
          "國泰永續高股息",
          51308
        ],
        [
          "2881",
          "富邦金",
          45956
        ],
        [
          "1303",
          "南亞",
          45684
        ],
        [
          "00992A",
          "主動群益科技創新",
          37529
        ],
        [
          "3481",
          "群創",
          31655
        ],
        [
          "00981A",
          "主動統一台股增長",
          24299
        ],
        [
          "2882",
          "國泰金",
          23092
        ]
      ],
      "fi_s": [
        [
          "2409",
          "友達",
          -88322
        ],
        [
          "2887",
          "台新新光金",
          -81920
        ],
        [
          "1402",
          "遠東新",
          -78086
        ],
        [
          "2337",
          "旺宏",
          -45692
        ],
        [
          "00991A",
          "主動復華未來50",
          -44623
        ],
        [
          "2618",
          "長榮航",
          -35373
        ],
        [
          "2880",
          "華南金",
          -32440
        ],
        [
          "2002",
          "中鋼",
          -26457
        ],
        [
          "2312",
          "金寶",
          -23538
        ],
        [
          "2382",
          "廣達",
          -21414
        ]
      ],
      "sit_b": [
        [
          "2382",
          "廣達",
          12553
        ],
        [
          "2603",
          "長榮",
          8950
        ],
        [
          "2891",
          "中信金",
          1078
        ],
        [
          "1802",
          "台玻",
          970
        ],
        [
          "00980A",
          "主動野村臺灣優選",
          749
        ],
        [
          "6770",
          "力積電",
          507
        ],
        [
          "2308",
          "台達電",
          296
        ],
        [
          "00935",
          "野村臺灣新科技50",
          205
        ],
        [
          "00988A",
          "主動統一全球創新",
          138
        ],
        [
          "0050",
          "元大台灣50",
          28
        ]
      ],
      "sit_s": [
        [
          "2881",
          "富邦金",
          -25525
        ],
        [
          "2882",
          "國泰金",
          -19876
        ],
        [
          "2303",
          "聯電",
          -19011
        ],
        [
          "2454",
          "聯發科",
          -1301
        ],
        [
          "3711",
          "日月光投控",
          -674
        ],
        [
          "2634",
          "漢翔",
          -3
        ],
        [
          "4961",
          "天鈺",
          -1
        ]
      ]
    },
    {
      "date": "2026-05-28",
      "fi_b": [
        [
          "6770",
          "力積電",
          120688
        ],
        [
          "2337",
          "旺宏",
          81634
        ],
        [
          "2408",
          "南亞科",
          62166
        ],
        [
          "2881",
          "富邦金",
          33906
        ],
        [
          "2356",
          "英業達",
          25878
        ],
        [
          "2449",
          "京元電子",
          22857
        ],
        [
          "2324",
          "仁寶",
          19507
        ],
        [
          "1402",
          "遠東新",
          18907
        ],
        [
          "2882",
          "國泰金",
          17727
        ],
        [
          "2317",
          "鴻海",
          12866
        ]
      ],
      "fi_s": [
        [
          "3481",
          "群創",
          -289339
        ],
        [
          "00981A",
          "主動統一台股增長",
          -93498
        ],
        [
          "00403A",
          "主動統一升級50",
          -80094
        ],
        [
          "2887",
          "台新新光金",
          -59197
        ],
        [
          "2344",
          "華邦電",
          -51734
        ],
        [
          "2880",
          "華南金",
          -46413
        ],
        [
          "009816",
          "凱基台灣TOP50",
          -41988
        ],
        [
          "0050",
          "元大台灣50",
          -39726
        ],
        [
          "2313",
          "華通",
          -33743
        ],
        [
          "00631L",
          "元大台灣50正2",
          -30592
        ]
      ],
      "sit_b": [
        [
          "2382",
          "廣達",
          12612
        ],
        [
          "2603",
          "長榮",
          11320
        ],
        [
          "2891",
          "中信金",
          8971
        ],
        [
          "00980A",
          "主動野村臺灣優選",
          739
        ],
        [
          "0050",
          "元大台灣50",
          688
        ],
        [
          "1802",
          "台玻",
          610
        ],
        [
          "2330",
          "台積電",
          465
        ],
        [
          "3711",
          "日月光投控",
          401
        ],
        [
          "4961",
          "天鈺",
          19
        ],
        [
          "6770",
          "力積電",
          15
        ]
      ],
      "sit_s": [
        [
          "2303",
          "聯電",
          -33811
        ],
        [
          "2881",
          "富邦金",
          -29134
        ],
        [
          "2882",
          "國泰金",
          -21170
        ],
        [
          "2454",
          "聯發科",
          -610
        ],
        [
          "2308",
          "台達電",
          -122
        ],
        [
          "3008",
          "大立光",
          -9
        ],
        [
          "2634",
          "漢翔",
          -6
        ]
      ]
    },
    {
      "date": "2026-05-29",
      "fi_b": [
        [
          "3481",
          "群創",
          163249
        ],
        [
          "00403A",
          "主動統一升級50",
          112163
        ],
        [
          "2317",
          "鴻海",
          80338
        ],
        [
          "2324",
          "仁寶",
          77121
        ],
        [
          "2409",
          "友達",
          66341
        ],
        [
          "1303",
          "南亞",
          59319
        ],
        [
          "2344",
          "華邦電",
          53583
        ],
        [
          "1402",
          "遠東新",
          37671
        ],
        [
          "1326",
          "台化",
          30567
        ],
        [
          "2610",
          "華航",
          29401
        ]
      ],
      "fi_s": [
        [
          "2887",
          "台新新光金",
          -62210
        ],
        [
          "2880",
          "華南金",
          -43962
        ],
        [
          "2303",
          "聯電",
          -28219
        ],
        [
          "2618",
          "長榮航",
          -20470
        ],
        [
          "00991A",
          "主動復華未來50",
          -17084
        ],
        [
          "00953B",
          "群益優選非投等債",
          -15885
        ],
        [
          "2892",
          "第一金",
          -11331
        ],
        [
          "2891",
          "中信金",
          -11117
        ],
        [
          "3711",
          "日月光投控",
          -10102
        ],
        [
          "2801",
          "彰銀",
          -9351
        ]
      ],
      "sit_b": [
        [
          "2382",
          "廣達",
          15430
        ],
        [
          "2603",
          "長榮",
          12001
        ],
        [
          "0050",
          "元大台灣50",
          5310
        ],
        [
          "00988A",
          "主動統一全球創新",
          1000
        ],
        [
          "2308",
          "台達電",
          607
        ],
        [
          "2330",
          "台積電",
          349
        ],
        [
          "00935",
          "野村臺灣新科技50",
          65
        ],
        [
          "4961",
          "天鈺",
          43
        ]
      ],
      "sit_s": [
        [
          "2303",
          "聯電",
          -28666
        ],
        [
          "2454",
          "聯發科",
          -1027
        ],
        [
          "1802",
          "台玻",
          -4
        ],
        [
          "2634",
          "漢翔",
          -4
        ]
      ]
    },
    {
      "date": "2026-06-01",
      "fi_b": [
        [
          "00403A",
          "主動統一升級50",
          111082
        ],
        [
          "3481",
          "群創",
          80703
        ],
        [
          "00981A",
          "主動統一台股增長",
          42017
        ],
        [
          "1802",
          "台玻",
          35838
        ],
        [
          "2887",
          "台新新光金",
          35320
        ],
        [
          "2408",
          "南亞科",
          27016
        ],
        [
          "00992A",
          "主動群益科技創新",
          26369
        ],
        [
          "2882",
          "國泰金",
          26002
        ],
        [
          "2883",
          "凱基金",
          25119
        ],
        [
          "3231",
          "緯創",
          24686
        ]
      ],
      "fi_s": [
        [
          "6770",
          "力積電",
          -158206
        ],
        [
          "2409",
          "友達",
          -110355
        ],
        [
          "2880",
          "華南金",
          -27363
        ],
        [
          "1605",
          "華新",
          -26096
        ],
        [
          "2618",
          "長榮航",
          -24439
        ],
        [
          "00988A",
          "主動統一全球創新",
          -24329
        ],
        [
          "0050",
          "元大台灣50",
          -22686
        ],
        [
          "1504",
          "東元",
          -19516
        ],
        [
          "00919",
          "群益台灣精選高息",
          -14841
        ],
        [
          "2355",
          "敬鵬",
          -14830
        ]
      ],
      "sit_b": [
        [
          "2891",
          "中信金",
          13697
        ],
        [
          "2603",
          "長榮",
          12843
        ],
        [
          "2382",
          "廣達",
          7281
        ],
        [
          "0050",
          "元大台灣50",
          2124
        ],
        [
          "2330",
          "台積電",
          458
        ],
        [
          "1802",
          "台玻",
          421
        ],
        [
          "4961",
          "天鈺",
          384
        ],
        [
          "00935",
          "野村臺灣新科技50",
          326
        ],
        [
          "6770",
          "力積電",
          199
        ],
        [
          "2308",
          "台達電",
          133
        ]
      ],
      "sit_s": [
        [
          "2303",
          "聯電",
          -38026
        ],
        [
          "2882",
          "國泰金",
          -22290
        ],
        [
          "2881",
          "富邦金",
          -9380
        ],
        [
          "3711",
          "日月光投控",
          -4657
        ],
        [
          "2454",
          "聯發科",
          -460
        ],
        [
          "2634",
          "漢翔",
          -8
        ]
      ]
    },
    {
      "date": "2026-06-02",
      "fi_b": [
        [
          "3231",
          "緯創",
          91902
        ],
        [
          "2303",
          "聯電",
          63633
        ],
        [
          "2353",
          "宏碁",
          51535
        ],
        [
          "2409",
          "友達",
          47814
        ],
        [
          "2337",
          "旺宏",
          27576
        ],
        [
          "2317",
          "鴻海",
          25502
        ],
        [
          "2890",
          "永豐金",
          23190
        ],
        [
          "0056",
          "元大高股息",
          20172
        ],
        [
          "2609",
          "陽明",
          19358
        ],
        [
          "1326",
          "台化",
          19072
        ]
      ],
      "fi_s": [
        [
          "3481",
          "群創",
          -208586
        ],
        [
          "00981A",
          "主動統一台股增長",
          -65843
        ],
        [
          "2883",
          "凱基金",
          -62750
        ],
        [
          "2887",
          "台新新光金",
          -51523
        ],
        [
          "2880",
          "華南金",
          -47653
        ],
        [
          "1802",
          "台玻",
          -47090
        ],
        [
          "2618",
          "長榮航",
          -38332
        ],
        [
          "00919",
          "群益台灣精選高息",
          -35459
        ],
        [
          "0050",
          "元大台灣50",
          -33890
        ],
        [
          "00991A",
          "主動復華未來50",
          -28158
        ]
      ],
      "sit_b": [
        [
          "2382",
          "廣達",
          37198
        ],
        [
          "2891",
          "中信金",
          17760
        ],
        [
          "3231",
          "緯創",
          17004
        ],
        [
          "2603",
          "長榮",
          14911
        ],
        [
          "2356",
          "英業達",
          9108
        ],
        [
          "2881",
          "富邦金",
          3491
        ],
        [
          "2376",
          "技嘉",
          3252
        ],
        [
          "2317",
          "鴻海",
          2072
        ],
        [
          "1802",
          "台玻",
          850
        ],
        [
          "00935",
          "野村臺灣新科技50",
          770
        ]
      ],
      "sit_s": [
        [
          "2303",
          "聯電",
          -115048
        ],
        [
          "2882",
          "國泰金",
          -11473
        ],
        [
          "3711",
          "日月光投控",
          -4716
        ],
        [
          "3037",
          "欣興",
          -4111
        ],
        [
          "00981A",
          "主動統一台股增長",
          -1503
        ],
        [
          "2454",
          "聯發科",
          -675
        ],
        [
          "2308",
          "台達電",
          -395
        ],
        [
          "2330",
          "台積電",
          -306
        ],
        [
          "8046",
          "南電",
          -199
        ],
        [
          "0050",
          "元大台灣50",
          -70
        ]
      ]
    },
    {
      "date": "2026-06-03",
      "fi_b": [
        [
          "00403A",
          "主動統一升級50",
          152511
        ],
        [
          "2303",
          "聯電",
          74044
        ],
        [
          "2890",
          "永豐金",
          55408
        ],
        [
          "3481",
          "群創",
          48121
        ],
        [
          "00981A",
          "主動統一台股增長",
          47308
        ],
        [
          "2834",
          "臺企銀",
          46348
        ],
        [
          "2892",
          "第一金",
          31932
        ],
        [
          "2317",
          "鴻海",
          28019
        ],
        [
          "2609",
          "陽明",
          27805
        ],
        [
          "2887",
          "台新新光金",
          27079
        ]
      ],
      "fi_s": [
        [
          "2344",
          "華邦電",
          -49531
        ],
        [
          "2618",
          "長榮航",
          -38677
        ],
        [
          "2409",
          "友達",
          -31129
        ],
        [
          "00919",
          "群益台灣精選高息",
          -27671
        ],
        [
          "00918",
          "大華優利高填息30",
          -25305
        ],
        [
          "2880",
          "華南金",
          -24247
        ],
        [
          "2382",
          "廣達",
          -24201
        ],
        [
          "2105",
          "正新",
          -20966
        ],
        [
          "2886",
          "兆豐金",
          -15378
        ],
        [
          "2408",
          "南亞科",
          -14403
        ]
      ],
      "sit_b": [
        [
          "2382",
          "廣達",
          33418
        ],
        [
          "00988A",
          "主動統一全球創新",
          20200
        ],
        [
          "3231",
          "緯創",
          18857
        ],
        [
          "2356",
          "英業達",
          15597
        ],
        [
          "2603",
          "長榮",
          12281
        ],
        [
          "2891",
          "中信金",
          7692
        ],
        [
          "2317",
          "鴻海",
          2775
        ],
        [
          "0050",
          "元大台灣50",
          1602
        ],
        [
          "2376",
          "技嘉",
          921
        ],
        [
          "2330",
          "台積電",
          654
        ]
      ],
      "sit_s": [
        [
          "2303",
          "聯電",
          -140694
        ],
        [
          "2881",
          "富邦金",
          -23948
        ],
        [
          "2882",
          "國泰金",
          -21914
        ],
        [
          "3711",
          "日月光投控",
          -3717
        ],
        [
          "3037",
          "欣興",
          -1908
        ],
        [
          "00981A",
          "主動統一台股增長",
          -1500
        ],
        [
          "3189",
          "景碩",
          -906
        ],
        [
          "2454",
          "聯發科",
          -900
        ],
        [
          "8046",
          "南電",
          -197
        ],
        [
          "6669",
          "緯穎",
          -36
        ]
      ]
    },
    {
      "date": "2026-06-04",
      "fi_b": [
        [
          "2303",
          "聯電",
          149147
        ],
        [
          "2834",
          "臺企銀",
          31853
        ],
        [
          "2892",
          "第一金",
          31430
        ],
        [
          "2884",
          "玉山金",
          26986
        ],
        [
          "2882",
          "國泰金",
          25038
        ],
        [
          "2801",
          "彰銀",
          22466
        ],
        [
          "2890",
          "永豐金",
          21935
        ],
        [
          "2609",
          "陽明",
          20265
        ],
        [
          "5880",
          "合庫金",
          20194
        ],
        [
          "2881",
          "富邦金",
          19027
        ]
      ],
      "fi_s": [
        [
          "2883",
          "凱基金",
          -150843
        ],
        [
          "2324",
          "仁寶",
          -99952
        ],
        [
          "2353",
          "宏碁",
          -64385
        ],
        [
          "3231",
          "緯創",
          -43099
        ],
        [
          "0050",
          "元大台灣50",
          -38480
        ],
        [
          "00981A",
          "主動統一台股增長",
          -34988
        ],
        [
          "00919",
          "群益台灣精選高息",
          -34723
        ],
        [
          "2382",
          "廣達",
          -32714
        ],
        [
          "2317",
          "鴻海",
          -28178
        ],
        [
          "2880",
          "華南金",
          -25644
        ]
      ],
      "sit_b": [
        [
          "2382",
          "廣達",
          33871
        ],
        [
          "2603",
          "長榮",
          9564
        ],
        [
          "00980A",
          "主動野村臺灣優選",
          1550
        ],
        [
          "2376",
          "技嘉",
          1191
        ],
        [
          "0050",
          "元大台灣50",
          1150
        ],
        [
          "3231",
          "緯創",
          962
        ],
        [
          "2317",
          "鴻海",
          856
        ],
        [
          "2330",
          "台積電",
          537
        ],
        [
          "006208",
          "富邦台50",
          461
        ],
        [
          "00935",
          "野村臺灣新科技50",
          413
        ]
      ],
      "sit_s": [
        [
          "2303",
          "聯電",
          -156281
        ],
        [
          "2881",
          "富邦金",
          -20713
        ],
        [
          "2882",
          "國泰金",
          -19921
        ],
        [
          "3711",
          "日月光投控",
          -4838
        ],
        [
          "2891",
          "中信金",
          -3300
        ],
        [
          "3189",
          "景碩",
          -891
        ],
        [
          "2454",
          "聯發科",
          -352
        ],
        [
          "2634",
          "漢翔",
          -1
        ]
      ]
    },
    {
      "date": "2026-06-05",
      "fi_b": [
        [
          "2303",
          "聯電",
          79930
        ],
        [
          "2609",
          "陽明",
          40555
        ],
        [
          "2887",
          "台新新光金",
          15793
        ],
        [
          "1718",
          "中纖",
          15061
        ],
        [
          "00712",
          "復華富時不動產",
          15053
        ],
        [
          "6770",
          "力積電",
          13159
        ],
        [
          "3481",
          "群創",
          12947
        ],
        [
          "00953B",
          "群益優選非投等債",
          12108
        ],
        [
          "2882",
          "國泰金",
          10810
        ],
        [
          "2027",
          "大成鋼",
          10403
        ]
      ],
      "fi_s": [
        [
          "2883",
          "凱基金",
          -101852
        ],
        [
          "00403A",
          "主動統一升級50",
          -93218
        ],
        [
          "00981A",
          "主動統一台股增長",
          -76728
        ],
        [
          "0050",
          "元大台灣50",
          -62926
        ],
        [
          "2409",
          "友達",
          -34522
        ],
        [
          "2344",
          "華邦電",
          -33722
        ],
        [
          "6282",
          "康舒",
          -31907
        ],
        [
          "2382",
          "廣達",
          -21412
        ],
        [
          "009816",
          "凱基台灣TOP50",
          -21294
        ],
        [
          "1402",
          "遠東新",
          -20649
        ]
      ],
      "sit_b": [
        [
          "2382",
          "廣達",
          19844
        ],
        [
          "0050",
          "元大台灣50",
          6297
        ],
        [
          "2330",
          "台積電",
          2911
        ],
        [
          "2881",
          "富邦金",
          1959
        ],
        [
          "2317",
          "鴻海",
          262
        ],
        [
          "00935",
          "野村臺灣新科技50",
          194
        ],
        [
          "3231",
          "緯創",
          137
        ],
        [
          "6669",
          "緯穎",
          57
        ],
        [
          "4961",
          "天鈺",
          21
        ],
        [
          "6770",
          "力積電",
          18
        ]
      ],
      "sit_s": [
        [
          "2303",
          "聯電",
          -75576
        ],
        [
          "00988A",
          "主動統一全球創新",
          -9233
        ],
        [
          "2891",
          "中信金",
          -6757
        ],
        [
          "00981A",
          "主動統一台股增長",
          -5750
        ],
        [
          "8046",
          "南電",
          -2475
        ],
        [
          "3037",
          "欣興",
          -1480
        ],
        [
          "2376",
          "技嘉",
          -769
        ],
        [
          "3711",
          "日月光投控",
          -708
        ],
        [
          "3189",
          "景碩",
          -517
        ],
        [
          "2603",
          "長榮",
          -464
        ]
      ]
    },
    {
      "date": "2026-06-08",
      "fi_b": [
        [
          "00953B",
          "群益優選非投等債",
          41193
        ],
        [
          "2344",
          "華邦電",
          30419
        ],
        [
          "2303",
          "聯電",
          30016
        ],
        [
          "00878",
          "國泰永續高股息",
          17474
        ],
        [
          "3702",
          "大聯大",
          13778
        ],
        [
          "3036",
          "文曄",
          12864
        ],
        [
          "2609",
          "陽明",
          11897
        ],
        [
          "00940",
          "元大台灣價值高息",
          9109
        ],
        [
          "00945B",
          "凱基美國非投等債",
          8726
        ],
        [
          "2890",
          "永豐金",
          8354
        ]
      ],
      "fi_s": [
        [
          "0050",
          "元大台灣50",
          -113326
        ],
        [
          "2883",
          "凱基金",
          -108622
        ],
        [
          "00403A",
          "主動統一升級50",
          -99851
        ],
        [
          "00981A",
          "主動統一台股增長",
          -44880
        ],
        [
          "2881",
          "富邦金",
          -38527
        ],
        [
          "1402",
          "遠東新",
          -35829
        ],
        [
          "2002",
          "中鋼",
          -32275
        ],
        [
          "1101",
          "台泥",
          -28958
        ],
        [
          "2610",
          "華航",
          -28514
        ],
        [
          "2324",
          "仁寶",
          -27266
        ]
      ],
      "sit_b": [
        [
          "2881",
          "富邦金",
          40314
        ],
        [
          "2382",
          "廣達",
          17760
        ],
        [
          "0050",
          "元大台灣50",
          8432
        ],
        [
          "2882",
          "國泰金",
          1030
        ],
        [
          "2330",
          "台積電",
          730
        ],
        [
          "2317",
          "鴻海",
          643
        ],
        [
          "00935",
          "野村臺灣新科技50",
          571
        ],
        [
          "2454",
          "聯發科",
          536
        ],
        [
          "8046",
          "南電",
          348
        ],
        [
          "3231",
          "緯創",
          267
        ]
      ],
      "sit_s": [
        [
          "2303",
          "聯電",
          -59986
        ],
        [
          "00988A",
          "主動統一全球創新",
          -10967
        ],
        [
          "00981A",
          "主動統一台股增長",
          -6730
        ],
        [
          "2603",
          "長榮",
          -3768
        ],
        [
          "3189",
          "景碩",
          -1547
        ],
        [
          "3037",
          "欣興",
          -328
        ],
        [
          "3008",
          "大立光",
          -27
        ],
        [
          "1802",
          "台玻",
          -1
        ],
        [
          "2634",
          "漢翔",
          -1
        ]
      ]
    },
    {
      "date": "2026-06-09",
      "fi_b": [
        [
          "2892",
          "第一金",
          64068
        ],
        [
          "2801",
          "彰銀",
          61779
        ],
        [
          "2887",
          "台新新光金",
          44816
        ],
        [
          "2834",
          "臺企銀",
          40676
        ],
        [
          "2884",
          "玉山金",
          39677
        ],
        [
          "00403A",
          "主動統一升級50",
          36865
        ],
        [
          "2890",
          "永豐金",
          36082
        ],
        [
          "00981A",
          "主動統一台股增長",
          35489
        ],
        [
          "2867",
          "三商壽",
          26148
        ],
        [
          "5880",
          "合庫金",
          22222
        ]
      ],
      "fi_s": [
        [
          "2409",
          "友達",
          -80413
        ],
        [
          "2883",
          "凱基金",
          -80409
        ],
        [
          "2344",
          "華邦電",
          -48095
        ],
        [
          "2324",
          "仁寶",
          -39354
        ],
        [
          "0050",
          "元大台灣50",
          -21647
        ],
        [
          "2002",
          "中鋼",
          -18019
        ],
        [
          "2881",
          "富邦金",
          -17485
        ],
        [
          "00919",
          "群益台灣精選高息",
          -16234
        ],
        [
          "1402",
          "遠東新",
          -16106
        ],
        [
          "00712",
          "復華富時不動產",
          -15726
        ]
      ],
      "sit_b": [
        [
          "2881",
          "富邦金",
          24527
        ],
        [
          "00981A",
          "主動統一台股增長",
          17410
        ],
        [
          "2382",
          "廣達",
          9612
        ],
        [
          "2330",
          "台積電",
          2670
        ],
        [
          "0050",
          "元大台灣50",
          2450
        ],
        [
          "2376",
          "技嘉",
          893
        ],
        [
          "8046",
          "南電",
          839
        ],
        [
          "2308",
          "台達電",
          787
        ],
        [
          "2454",
          "聯發科",
          637
        ],
        [
          "3231",
          "緯創",
          553
        ]
      ],
      "sit_s": [
        [
          "2303",
          "聯電",
          -67388
        ],
        [
          "2891",
          "中信金",
          -10158
        ],
        [
          "2603",
          "長榮",
          -4250
        ],
        [
          "1802",
          "台玻",
          -3600
        ],
        [
          "2882",
          "國泰金",
          -653
        ],
        [
          "3189",
          "景碩",
          -356
        ],
        [
          "2356",
          "英業達",
          -76
        ],
        [
          "3711",
          "日月光投控",
          -25
        ],
        [
          "6669",
          "緯穎",
          -2
        ]
      ]
    }
  ]
}