{
  "updated": "2026/06/09 14:01",
  "indices": [
    {
      "symbol": "^KS11",
      "name": "KOSPI",
      "price": 8073.35,
      "change": 588.94,
      "pct": 7.87,
      "date": "06/09"
    },
    {
      "symbol": "^KQ11",
      "name": "KOSDAQ",
      "price": 970.32,
      "change": 58.93,
      "pct": 6.47,
      "date": "06/09"
    }
  ],
  "semi": [
    {
      "symbol": "005930.KS",
      "name": "三星電子",
      "price": 321000.0,
      "change": 25500.0,
      "pct": 8.63,
      "date": "06/09"
    },
    {
      "symbol": "000660.KS",
      "name": "SK 海力士",
      "price": 2201000.0,
      "change": 290000.0,
      "pct": 15.18,
      "date": "06/09"
    },
    {
      "symbol": "042700.KS",
      "name": "漢美半導體",
      "price": 276000.0,
      "change": 22500.0,
      "pct": 8.88,
      "date": "06/09"
    },
    {
      "symbol": "009150.KS",
      "name": "三星電機",
      "price": 1950000.0,
      "change": 286000.0,
      "pct": 17.19,
      "date": "06/09"
    }
  ],
  "display": [
    {
      "symbol": "034220.KS",
      "name": "LG Display",
      "price": 13850.0,
      "change": -170.0,
      "pct": -1.21,
      "date": "06/09"
    }
  ],
  "camera": [
    {
      "symbol": "011070.KS",
      "name": "LG Innotek",
      "price": 1150000.0,
      "change": 55000.0,
      "pct": 5.02,
      "date": "06/09"
    }
  ]
}