{
  "updated": "2026/06/05 23:36",
  "stocks": {
    "TSM": {
      "rsi14": 54.9,
      "rsi21": 56.4,
      "bias20": 2.0,
      "bias60": 11.2
    },
    "MU": {
      "rsi14": 60.9,
      "rsi21": 63.6,
      "bias20": 8.3,
      "bias60": 57.6
    },
    "TSLA": {
      "rsi14": 43.7,
      "rsi21": 47.1,
      "bias20": -5.9,
      "bias60": 1.8
    },
    "EWT": {
      "rsi14": 56.7,
      "rsi21": 60.4,
      "bias20": 1.5,
      "bias60": 17.2
    },
    "AMZN": {
      "rsi14": 43.0,
      "rsi21": 48.2,
      "bias20": -4.3,
      "bias60": 3.6
    },
    "MSFT": {
      "rsi14": 49.8,
      "rsi21": 51.5,
      "bias20": -0.2,
      "bias60": 4.2
    },
    "GOOGL": {
      "rsi14": 46.6,
      "rsi21": 51.0,
      "bias20": -4.3,
      "bias60": 6.6
    },
    "ORCL": {
      "rsi14": 57.6,
      "rsi21": 58.8,
      "bias20": 6.6,
      "bias60": 24.4
    },
    "META": {
      "rsi14": 47.2,
      "rsi21": 47.5,
      "bias20": -0.3,
      "bias60": -1.1
    },
    "IBM": {
      "rsi14": 59.5,
      "rsi21": 59.2,
      "bias20": 11.6,
      "bias60": 16.6
    },
    "AAPL": {
      "rsi14": 68.3,
      "rsi21": 67.8,
      "bias20": 2.9,
      "bias60": 13.5
    },
    "NVDA": {
      "rsi14": 45.8,
      "rsi21": 49.4,
      "bias20": -5.1,
      "bias60": 4.3
    },
    "AMD": {
      "rsi14": 58.5,
      "rsi21": 62.4,
      "bias20": 1.8,
      "bias60": 45.2
    },
    "AVGO": {
      "rsi14": 41.9,
      "rsi21": 46.6,
      "bias20": -8.0,
      "bias60": 2.5
    },
    "MRVL": {
      "rsi14": 74.1,
      "rsi21": 74.1,
      "bias20": 37.4,
      "bias60": 88.1
    },
    "INTC": {
      "rsi14": 47.1,
      "rsi21": 53.2,
      "bias20": -10.9,
      "bias60": 26.9
    },
    "QCOM": {
      "rsi14": 54.4,
      "rsi21": 57.1,
      "bias20": -0.0,
      "bias60": 33.3
    },
    "ARM": {
      "rsi14": 63.7,
      "rsi21": 65.4,
      "bias20": 21.2,
      "bias60": 70.9
    },
    "COHR": {
      "rsi14": 58.4,
      "rsi21": 59.2,
      "bias20": 4.7,
      "bias60": 24.6
    },
    "LITE": {
      "rsi14": 50.1,
      "rsi21": 51.6,
      "bias20": -2.4,
      "bias60": 7.3
    },
    "CIEN": {
      "rsi14": 43.5,
      "rsi21": 48.2,
      "bias20": -10.0,
      "bias60": 3.7
    },
    "AAOI": {
      "rsi14": 56.0,
      "rsi21": 56.4,
      "bias20": 6.7,
      "bias60": 32.5
    },
    "VIAV": {
      "rsi14": 50.0,
      "rsi21": 52.9,
      "bias20": -3.1,
      "bias60": 12.6
    },
    "VST": {
      "rsi14": 46.6,
      "rsi21": 47.3,
      "bias20": 0.0,
      "bias60": -3.0
    },
    "CEG": {
      "rsi14": 37.3,
      "rsi21": 40.3,
      "bias20": -7.8,
      "bias60": -11.5
    },
    "GEV": {
      "rsi14": 38.6,
      "rsi21": 43.7,
      "bias20": -7.3,
      "bias60": -3.9
    },
    "ETN": {
      "rsi14": 49.9,
      "rsi21": 51.3,
      "bias20": 0.4,
      "bias60": 2.8
    },
    "NEE": {
      "rsi14": 38.2,
      "rsi21": 40.2,
      "bias20": -4.2,
      "bias60": -6.8
    },
    "SPY": {
      "rsi14": 57.1,
      "rsi21": 60.4,
      "bias20": -0.0,
      "bias60": 5.9
    },
    "QQQ": {
      "rsi14": 56.7,
      "rsi21": 61.2,
      "bias20": -0.3,
      "bias60": 9.9
    },
    "VOO": {
      "rsi14": 57.1,
      "rsi21": 60.5,
      "bias20": -0.0,
      "bias60": 6.0
    },
    "SCHD": {
      "rsi14": 61.8,
      "rsi21": 61.8,
      "bias20": 1.0,
      "bias60": 3.9
    },
    "VGT": {
      "rsi14": 57.6,
      "rsi21": 61.4,
      "bias20": 0.8,
      "bias60": 14.8
    },
    "SOXX": {
      "rsi14": 59.1,
      "rsi21": 62.3,
      "bias20": 2.9,
      "bias60": 27.4
    },
    "GLD": {
      "rsi14": 34.0,
      "rsi21": 37.9,
      "bias20": -4.6,
      "bias60": -6.7
    },
    "TLT": {
      "rsi14": 51.2,
      "rsi21": 49.6,
      "bias20": 0.6,
      "bias60": -0.3
    },
    "ARKK": {
      "rsi14": 45.1,
      "rsi21": 47.9,
      "bias20": -3.1,
      "bias60": 1.3
    },
    "2330.TW": {
      "rsi14": 61.3,
      "rsi21": 61.7,
      "bias20": 3.3,
      "bias60": 12.9
    },
    "2454.TW": {
      "rsi14": 63.9,
      "rsi21": 66.2,
      "bias20": 8.6,
      "bias60": 61.5
    },
    "3711.TW": {
      "rsi14": 54.9,
      "rsi21": 57.8,
      "bias20": 1.7,
      "bias60": 24.2
    },
    "2303.TW": {
      "rsi14": 62.4,
      "rsi21": 64.8,
      "bias20": 7.9,
      "bias60": 54.1
    },
    "3008.TW": {
      "rsi14": 60.2,
      "rsi21": 61.4,
      "bias20": 7.0,
      "bias60": 33.4
    },
    "6770.TW": {
      "rsi14": 55.7,
      "rsi21": 56.9,
      "bias20": 6.0,
      "bias60": 18.9
    },
    "1802.TW": {
      "rsi14": 47.7,
      "rsi21": 50.6,
      "bias20": -2.4,
      "bias60": 4.5
    },
    "3037.TW": {
      "rsi14": 52.5,
      "rsi21": 56.5,
      "bias20": -0.9,
      "bias60": 26.0
    },
    "8046.TW": {
      "rsi14": 49.1,
      "rsi21": 52.3,
      "bias20": -2.6,
      "bias60": 12.5
    },
    "3189.TW": {
      "rsi14": 65.2,
      "rsi21": 66.1,
      "bias20": 15.5,
      "bias60": 50.1
    },
    "3149.TW": {
      "rsi14": 84.5,
      "rsi21": 79.8,
      "bias20": 36.4,
      "bias60": 73.8
    },
    "2317.TW": {
      "rsi14": 63.1,
      "rsi21": 63.8,
      "bias20": 7.5,
      "bias60": 23.9
    },
    "2382.TW": {
      "rsi14": 65.8,
      "rsi21": 64.2,
      "bias20": 15.8,
      "bias60": 23.1
    },
    "3231.TW": {
      "rsi14": 61.3,
      "rsi21": 61.3,
      "bias20": 12.9,
      "bias60": 22.0
    },
    "2356.TW": {
      "rsi14": 70.0,
      "rsi21": 70.5,
      "bias20": 23.1,
      "bias60": 52.1
    },
    "2376.TW": {
      "rsi14": 63.8,
      "rsi21": 64.8,
      "bias20": 8.2,
      "bias60": 28.9
    },
    "6669.TW": {
      "rsi14": 61.9,
      "rsi21": 61.3,
      "bias20": 5.6,
      "bias60": 26.5
    },
    "2308.TW": {
      "rsi14": 54.8,
      "rsi21": 57.5,
      "bias20": 2.8,
      "bias60": 20.7
    },
    "2603.TW": {
      "rsi14": 66.3,
      "rsi21": 63.8,
      "bias20": 7.7,
      "bias60": 11.2
    },
    "2881.TW": {
      "rsi14": 85.6,
      "rsi21": 81.2,
      "bias20": 14.9,
      "bias60": 26.3
    },
    "2882.TW": {
      "rsi14": 88.0,
      "rsi21": 82.5,
      "bias20": 20.4,
      "bias60": 30.1
    },
    "2891.TW": {
      "rsi14": 71.0,
      "rsi21": 69.7,
      "bias20": 12.7,
      "bias60": 20.8
    },
    "8033.TW": {
      "rsi14": 43.9,
      "rsi21": 45.0,
      "bias20": -1.9,
      "bias60": -5.4
    },
    "2634.TW": {
      "rsi14": 46.0,
      "rsi21": 45.3,
      "bias20": 0.2,
      "bias60": -3.2
    },
    "4961.TW": {
      "rsi14": 50.2,
      "rsi21": 52.8,
      "bias20": -2.3,
      "bias60": 6.3
    },
    "0050.TW": {
      "rsi14": 64.5,
      "rsi21": 66.1,
      "bias20": 4.5,
      "bias60": 18.2
    },
    "006208.TW": {
      "rsi14": 65.0,
      "rsi21": 66.4,
      "bias20": 4.6,
      "bias60": 18.0
    },
    "00878.TW": {
      "rsi14": 76.0,
      "rsi21": 76.5,
      "bias20": 10.1,
      "bias60": 28.1
    },
    "00919.TW": {
      "rsi14": 84.0,
      "rsi21": 81.6,
      "bias20": 10.9,
      "bias60": 24.1
    },
    "00929.TW": {
      "rsi14": 70.9,
      "rsi21": 72.3,
      "bias20": 7.1,
      "bias60": 29.8
    },
    "00940.TW": {
      "rsi14": 77.9,
      "rsi21": 76.4,
      "bias20": 7.5,
      "bias60": 19.1
    },
    "00988A.TW": {
      "rsi14": 60.3,
      "rsi21": 62.9,
      "bias20": 3.9,
      "bias60": 28.2
    },
    "00981A.TW": {
      "rsi14": 58.3,
      "rsi21": 61.4,
      "bias20": 2.2,
      "bias60": 19.2
    },
    "00935.TW": {
      "rsi14": 61.7,
      "rsi21": 64.6,
      "bias20": 4.1,
      "bias60": 25.4
    },
    "00980A.TW": {
      "rsi14": 60.1,
      "rsi21": 62.5,
      "bias20": 3.0,
      "bias60": 18.6
    },
    "00631L.TW": {
      "rsi14": 63.1,
      "rsi21": 64.8,
      "bias20": 7.7,
      "bias60": 32.5
    },
    "00675L.TW": {
      "rsi14": 62.8,
      "rsi21": 64.4,
      "bias20": 8.2,
      "bias60": 33.4
    },
    "00663L.TW": {
      "rsi14": 62.9,
      "rsi21": 64.5,
      "bias20": 8.2,
      "bias60": 33.5
    }
  }
}