{
  "updated": "2026/07/06 18:01",
  "stocks": {
    "TSM": {
      "rsi14": 50.2,
      "rsi21": 52.1,
      "bias20": -0.7,
      "bias60": 5.8
    },
    "MU": {
      "rsi14": 48.5,
      "rsi21": 52.3,
      "bias20": -6.5,
      "bias60": 24.5
    },
    "TSLA": {
      "rsi14": 46.8,
      "rsi21": 47.5,
      "bias20": -1.4,
      "bias60": -1.8
    },
    "EWT": {
      "rsi14": 53.3,
      "rsi21": 55.8,
      "bias20": 0.5,
      "bias60": 9.9
    },
    "EWJ": {
      "rsi14": 52.3,
      "rsi21": 53.5,
      "bias20": 0.2,
      "bias60": 2.6
    },
    "AMZN": {
      "rsi14": 48.7,
      "rsi21": 48.4,
      "bias20": 1.0,
      "bias60": -4.2
    },
    "MSFT": {
      "rsi14": 49.9,
      "rsi21": 48.3,
      "bias20": 0.9,
      "bias60": -3.8
    },
    "GOOGL": {
      "rsi14": 49.5,
      "rsi21": 49.8,
      "bias20": 0.4,
      "bias60": -1.1
    },
    "ORCL": {
      "rsi14": 26.7,
      "rsi21": 33.9,
      "bias20": -21.2,
      "bias60": -23.1
    },
    "META": {
      "rsi14": 49.7,
      "rsi21": 48.2,
      "bias20": 1.1,
      "bias60": -4.9
    },
    "IBM": {
      "rsi14": 61.6,
      "rsi21": 59.4,
      "bias20": 6.0,
      "bias60": 14.5
    },
    "AAPL": {
      "rsi14": 60.3,
      "rsi21": 58.4,
      "bias20": 4.7,
      "bias60": 7.0
    },
    "NVDA": {
      "rsi14": 41.2,
      "rsi21": 44.0,
      "bias20": -4.3,
      "bias60": -5.9
    },
    "AMD": {
      "rsi14": 52.3,
      "rsi21": 55.2,
      "bias20": 0.2,
      "bias60": 21.3
    },
    "AVGO": {
      "rsi14": 39.7,
      "rsi21": 42.7,
      "bias20": -6.1,
      "bias60": -10.9
    },
    "MRVL": {
      "rsi14": 46.5,
      "rsi21": 50.6,
      "bias20": -13.0,
      "bias60": 17.6
    },
    "INTC": {
      "rsi14": 49.1,
      "rsi21": 52.5,
      "bias20": -2.3,
      "bias60": 14.3
    },
    "QCOM": {
      "rsi14": 38.2,
      "rsi21": 43.3,
      "bias20": -14.3,
      "bias60": -7.4
    },
    "ARM": {
      "rsi14": 44.8,
      "rsi21": 49.5,
      "bias20": -13.3,
      "bias60": 14.4
    },
    "COHR": {
      "rsi14": 41.2,
      "rsi21": 45.1,
      "bias20": -13.4,
      "bias60": -7.5
    },
    "LITE": {
      "rsi14": 37.7,
      "rsi21": 42.1,
      "bias20": -15.4,
      "bias60": -18.6
    },
    "CIEN": {
      "rsi14": 37.4,
      "rsi21": 41.5,
      "bias20": -8.3,
      "bias60": -17.6
    },
    "AAOI": {
      "rsi14": 37.7,
      "rsi21": 42.1,
      "bias20": -25.5,
      "bias60": -26.9
    },
    "VIAV": {
      "rsi14": 37.1,
      "rsi21": 42.1,
      "bias20": -15.0,
      "bias60": -14.2
    },
    "VST": {
      "rsi14": 44.4,
      "rsi21": 47.0,
      "bias20": -2.9,
      "bias60": -2.6
    },
    "CEG": {
      "rsi14": 34.1,
      "rsi21": 37.8,
      "bias20": -7.4,
      "bias60": -14.7
    },
    "GEV": {
      "rsi14": 57.2,
      "rsi21": 56.5,
      "bias20": 8.8,
      "bias60": 7.9
    },
    "ETN": {
      "rsi14": 47.1,
      "rsi21": 48.8,
      "bias20": -2.1,
      "bias60": -1.7
    },
    "NEE": {
      "rsi14": 53.9,
      "rsi21": 51.0,
      "bias20": 2.2,
      "bias60": -1.5
    },
    "SPY": {
      "rsi14": 54.1,
      "rsi21": 55.1,
      "bias20": 0.6,
      "bias60": 2.2
    },
    "QQQ": {
      "rsi14": 48.3,
      "rsi21": 51.1,
      "bias20": -1.1,
      "bias60": 2.5
    },
    "VOO": {
      "rsi14": 54.5,
      "rsi21": 55.4,
      "bias20": 0.7,
      "bias60": 2.3
    },
    "SCHD": {
      "rsi14": 59.2,
      "rsi21": 58.2,
      "bias20": 1.2,
      "bias60": 2.5
    },
    "VGT": {
      "rsi14": 47.6,
      "rsi21": 50.8,
      "bias20": -1.9,
      "bias60": 3.3
    },
    "SOXX": {
      "rsi14": 47.3,
      "rsi21": 50.8,
      "bias20": -5.2,
      "bias60": 8.7
    },
    "GLD": {
      "rsi14": 42.0,
      "rsi21": 41.0,
      "bias20": -1.4,
      "bias60": -8.2
    },
    "TLT": {
      "rsi14": 47.7,
      "rsi21": 49.2,
      "bias20": -0.3,
      "bias60": 0.1
    },
    "ARKK": {
      "rsi14": 58.5,
      "rsi21": 56.5,
      "bias20": 4.3,
      "bias60": 5.3
    },
    "2330.TW": {
      "rsi14": 58.3,
      "rsi21": 58.5,
      "bias20": 3.1,
      "bias60": 8.4
    },
    "2454.TW": {
      "rsi14": 49.7,
      "rsi21": 53.4,
      "bias20": -3.5,
      "bias60": 16.3
    },
    "3711.TW": {
      "rsi14": 61.1,
      "rsi21": 61.3,
      "bias20": 9.2,
      "bias60": 23.1
    },
    "2303.TW": {
      "rsi14": 62.3,
      "rsi21": 63.9,
      "bias20": 9.1,
      "bias60": 42.5
    },
    "3008.TW": {
      "rsi14": 47.5,
      "rsi21": 52.3,
      "bias20": -8.1,
      "bias60": 17.9
    },
    "6770.TW": {
      "rsi14": 48.0,
      "rsi21": 50.6,
      "bias20": -2.2,
      "bias60": 9.1
    },
    "1802.TW": {
      "rsi14": 48.6,
      "rsi21": 50.0,
      "bias20": 0.1,
      "bias60": -0.9
    },
    "3037.TW": {
      "rsi14": 46.2,
      "rsi21": 49.7,
      "bias20": -4.7,
      "bias60": 3.6
    },
    "8046.TW": {
      "rsi14": 57.4,
      "rsi21": 58.1,
      "bias20": 10.5,
      "bias60": 20.9
    },
    "3189.TW": {
      "rsi14": 53.1,
      "rsi21": 55.9,
      "bias20": 2.4,
      "bias60": 25.7
    },
    "3149.TW": {
      "rsi14": 51.2,
      "rsi21": 54.9,
      "bias20": -4.2,
      "bias60": 29.5
    },
    "2317.TW": {
      "rsi14": 43.4,
      "rsi21": 47.3,
      "bias20": -3.9,
      "bias60": 0.3
    },
    "2382.TW": {
      "rsi14": 58.1,
      "rsi21": 57.8,
      "bias20": 1.6,
      "bias60": 9.6
    },
    "3231.TW": {
      "rsi14": 50.6,
      "rsi21": 52.3,
      "bias20": -0.6,
      "bias60": 5.2
    },
    "2356.TW": {
      "rsi14": 53.9,
      "rsi21": 55.9,
      "bias20": 0.6,
      "bias60": 14.7
    },
    "2376.TW": {
      "rsi14": 49.6,
      "rsi21": 52.0,
      "bias20": -1.1,
      "bias60": 4.8
    },
    "6669.TW": {
      "rsi14": 53.5,
      "rsi21": 53.3,
      "bias20": 4.0,
      "bias60": 5.6
    },
    "2308.TW": {
      "rsi14": 45.0,
      "rsi21": 47.1,
      "bias20": -4.6,
      "bias60": -5.3
    },
    "2603.TW": {
      "rsi14": 51.7,
      "rsi21": 51.0,
      "bias20": 0.1,
      "bias60": 0.5
    },
    "2881.TW": {
      "rsi14": 53.9,
      "rsi21": 58.4,
      "bias20": -2.7,
      "bias60": 17.3
    },
    "2882.TW": {
      "rsi14": 46.1,
      "rsi21": 51.5,
      "bias20": -7.4,
      "bias60": 10.3
    },
    "2891.TW": {
      "rsi14": 63.5,
      "rsi21": 64.3,
      "bias20": 2.1,
      "bias60": 17.3
    },
    "8033.TW": {
      "rsi14": 87.5,
      "rsi21": 80.9,
      "bias20": 48.9,
      "bias60": 53.7
    },
    "2634.TW": {
      "rsi14": 76.9,
      "rsi21": 72.3,
      "bias20": 19.8,
      "bias60": 24.3
    },
    "4961.TW": {
      "rsi14": 64.3,
      "rsi21": 61.2,
      "bias20": 8.8,
      "bias60": 11.3
    },
    "0050.TW": {
      "rsi14": 58.1,
      "rsi21": 59.5,
      "bias20": 2.3,
      "bias60": 10.3
    },
    "006208.TW": {
      "rsi14": 58.5,
      "rsi21": 59.8,
      "bias20": 2.5,
      "bias60": 10.6
    },
    "00878.TW": {
      "rsi14": 62.8,
      "rsi21": 65.3,
      "bias20": 1.6,
      "bias60": 15.8
    },
    "00919.TW": {
      "rsi14": 59.5,
      "rsi21": 62.9,
      "bias20": 0.0,
      "bias60": 12.3
    },
    "00929.TW": {
      "rsi14": 61.2,
      "rsi21": 62.7,
      "bias20": 3.3,
      "bias60": 17.7
    },
    "00940.TW": {
      "rsi14": 62.0,
      "rsi21": 63.2,
      "bias20": 2.0,
      "bias60": 11.1
    },
    "00403A.TW": {
      "rsi14": 53.6,
      "rsi21": 54.3,
      "bias20": 1.6,
      "bias60": null
    },
    "00988A.TW": {
      "rsi14": 45.9,
      "rsi21": 50.5,
      "bias20": -4.5,
      "bias60": 5.8
    },
    "00981A.TW": {
      "rsi14": 53.5,
      "rsi21": 55.9,
      "bias20": 1.0,
      "bias60": 7.9
    },
    "00935.TW": {
      "rsi14": 54.4,
      "rsi21": 57.0,
      "bias20": 1.0,
      "bias60": 10.8
    },
    "00980A.TW": {
      "rsi14": 52.7,
      "rsi21": 55.1,
      "bias20": 0.3,
      "bias60": 6.9
    },
    "00631L.TW": {
      "rsi14": 56.9,
      "rsi21": 58.0,
      "bias20": 4.1,
      "bias60": 17.1
    },
    "00675L.TW": {
      "rsi14": 56.2,
      "rsi21": 57.4,
      "bias20": 3.8,
      "bias60": 17.3
    },
    "00663L.TW": {
      "rsi14": 56.3,
      "rsi21": 57.5,
      "bias20": 3.8,
      "bias60": 17.3
    }
  }
}