{
  "updated": "2026/06/05 19:00",
  "date": "2026-06-05",
  "stocks": {
    "2330": {
      "fi": -17839581,
      "sit": 2911428,
      "dealer": 516810
    },
    "2454": {
      "fi": 414722,
      "sit": -108257,
      "dealer": -357424
    },
    "3711": {
      "fi": -850510,
      "sit": -707065,
      "dealer": 178641
    },
    "2303": {
      "fi": 79930463,
      "sit": -75575871,
      "dealer": 8778188
    },
    "3008": {
      "fi": 29076,
      "sit": -147585,
      "dealer": -63465
    },
    "6770": {
      "fi": 13159351,
      "sit": 18000,
      "dealer": -10039758
    },
    "1802": {
      "fi": -8980780,
      "sit": -3000,
      "dealer": -1784643
    },
    "3037": {
      "fi": -833510,
      "sit": -1480000,
      "dealer": -219476
    },
    "8046": {
      "fi": 1571058,
      "sit": -2475000,
      "dealer": -6959
    },
    "3189": {
      "fi": 2327784,
      "sit": -516905,
      "dealer": -807601
    },
    "3149": {
      "fi": 2745650,
      "sit": 0,
      "dealer": -50047
    },
    "2317": {
      "fi": -3318613,
      "sit": 262734,
      "dealer": -2323075
    },
    "2382": {
      "fi": -21411443,
      "sit": 19844766,
      "dealer": 90756
    },
    "3231": {
      "fi": 4079787,
      "sit": 137581,
      "dealer": -509609
    },
    "2356": {
      "fi": 9677913,
      "sit": -96299,
      "dealer": -1218623
    },
    "2376": {
      "fi": 5346355,
      "sit": -768393,
      "dealer": -126144
    },
    "6669": {
      "fi": -137861,
      "sit": 57968,
      "dealer": -3116
    },
    "2308": {
      "fi": -2360808,
      "sit": -66097,
      "dealer": 54547
    },
    "2603": {
      "fi": -4573095,
      "sit": -463525,
      "dealer": -522241
    },
    "2881": {
      "fi": -4349520,
      "sit": 1959746,
      "dealer": 57263
    },
    "2882": {
      "fi": 10810614,
      "sit": -278827,
      "dealer": 98866
    },
    "2891": {
      "fi": -13432073,
      "sit": -6756030,
      "dealer": 412863
    },
    "8033": {
      "fi": -546585,
      "sit": 0,
      "dealer": -16167
    },
    "2634": {
      "fi": -1123532,
      "sit": -5000,
      "dealer": -40815
    },
    "4961": {
      "fi": 56285,
      "sit": 21000,
      "dealer": -16935
    }
  }
}