{
  "updated": "2026/06/12 13:21",
  "indices": [
    {
      "symbol": "^TWII",
      "name": "加權指數",
      "price": 44202.93,
      "change": 1053.47,
      "pct": 2.44,
      "date": "06/12"
    },
    {
      "symbol": "00631L.TW",
      "name": "元大台灣50正2",
      "price": 34.99,
      "change": 1.76,
      "pct": 5.3,
      "date": "06/12",
      "nav": 33.46,
      "premium": -0.69
    }
  ],
  "semi": [
    {
      "symbol": "2330.TW",
      "name": "台積電",
      "price": 2300.0,
      "change": 50.0,
      "pct": 2.22,
      "date": "06/12"
    },
    {
      "symbol": "2454.TW",
      "name": "聯發科",
      "price": 4215.0,
      "change": 130.0,
      "pct": 3.18,
      "date": "06/12"
    },
    {
      "symbol": "3711.TW",
      "name": "ASE 日月光",
      "price": 589.0,
      "change": 45.0,
      "pct": 8.27,
      "date": "06/12"
    },
    {
      "symbol": "2303.TW",
      "name": "聯電",
      "price": 135.0,
      "change": 10.0,
      "pct": 8.0,
      "date": "06/12"
    },
    {
      "symbol": "3008.TW",
      "name": "大立光",
      "price": 4075.0,
      "change": -90.0,
      "pct": -2.16,
      "date": "06/12"
    },
    {
      "symbol": "6770.TW",
      "name": "力積電",
      "price": 67.4,
      "change": 3.0,
      "pct": 4.66,
      "date": "06/12"
    }
  ],
  "glass": [
    {
      "symbol": "1802.TW",
      "name": "台玻",
      "price": 64.6,
      "change": 5.3,
      "pct": 8.94,
      "date": "06/12"
    },
    {
      "symbol": "3037.TW",
      "name": "欣興",
      "price": 909.0,
      "change": 55.0,
      "pct": 6.44,
      "date": "06/12"
    },
    {
      "symbol": "8046.TW",
      "name": "南電",
      "price": 825.0,
      "change": 18.0,
      "pct": 2.23,
      "date": "06/12"
    },
    {
      "symbol": "3189.TW",
      "name": "景碩",
      "price": 618.0,
      "change": -1.0,
      "pct": -0.16,
      "date": "06/12"
    },
    {
      "symbol": "3149.TW",
      "name": "正達",
      "price": 82.9,
      "change": 2.4,
      "pct": 2.98,
      "date": "06/12"
    }
  ],
  "old_ai": [
    {
      "symbol": "2317.TW",
      "name": "鴻海",
      "price": 262.5,
      "change": 4.0,
      "pct": 1.55,
      "date": "06/12"
    },
    {
      "symbol": "2382.TW",
      "name": "廣達",
      "price": 377.0,
      "change": 7.0,
      "pct": 1.89,
      "date": "06/12"
    },
    {
      "symbol": "3231.TW",
      "name": "緯創",
      "price": 157.0,
      "change": 4.5,
      "pct": 2.95,
      "date": "06/12"
    },
    {
      "symbol": "2356.TW",
      "name": "英業達",
      "price": 66.4,
      "change": 1.0,
      "pct": 1.53,
      "date": "06/12"
    },
    {
      "symbol": "2376.TW",
      "name": "技嘉",
      "price": 343.0,
      "change": 3.0,
      "pct": 0.88,
      "date": "06/12"
    },
    {
      "symbol": "6669.TW",
      "name": "緯穎",
      "price": 4900.0,
      "change": 0.0,
      "pct": 0.0,
      "date": "06/12"
    }
  ],
  "power_ship": [
    {
      "symbol": "2308.TW",
      "name": "台達電",
      "price": 2220.0,
      "change": 60.0,
      "pct": 2.78,
      "date": "06/12"
    },
    {
      "symbol": "2603.TW",
      "name": "長榮",
      "price": 227.5,
      "change": 1.5,
      "pct": 0.66,
      "date": "06/12"
    }
  ],
  "finance": [
    {
      "symbol": "2881.TW",
      "name": "富邦金",
      "price": 121.0,
      "change": -4.5,
      "pct": -3.59,
      "date": "06/12"
    },
    {
      "symbol": "2882.TW",
      "name": "國泰金",
      "price": 100.0,
      "change": -0.5,
      "pct": -0.5,
      "date": "06/12"
    },
    {
      "symbol": "2891.TW",
      "name": "中信金",
      "price": 67.1,
      "change": -0.4,
      "pct": -0.59,
      "date": "06/12"
    }
  ],
  "drone": [
    {
      "symbol": "8033.TW",
      "name": "雷虎科技",
      "price": 131.0,
      "change": 4.5,
      "pct": 3.56,
      "date": "06/12"
    },
    {
      "symbol": "2634.TW",
      "name": "漢翔航空",
      "price": 47.35,
      "change": 1.15,
      "pct": 2.49,
      "date": "06/12"
    },
    {
      "symbol": "4961.TW",
      "name": "鼎天國際",
      "price": 166.5,
      "change": 3.5,
      "pct": 2.15,
      "date": "06/12"
    }
  ],
  "etf": [
    {
      "symbol": "0050.TW",
      "name": "元大台灣50",
      "price": 102.15,
      "change": 2.3,
      "pct": 2.3,
      "date": "06/12",
      "nav": 99.83,
      "premium": 0.02
    },
    {
      "symbol": "006208.TW",
      "name": "富邦台50",
      "price": 236.8,
      "change": 5.8,
      "pct": 2.51,
      "date": "06/12",
      "nav": 231.8,
      "premium": -0.35
    },
    {
      "symbol": "00878.TW",
      "name": "國泰永續高股息",
      "price": 32.19,
      "change": 0.59,
      "pct": 1.87,
      "date": "06/12",
      "nav": 31.77,
      "premium": -0.54
    },
    {
      "symbol": "00919.TW",
      "name": "群益台灣精選高息",
      "price": 30.26,
      "change": 0.07,
      "pct": 0.23,
      "date": "06/12",
      "nav": 30.23,
      "premium": -0.13
    },
    {
      "symbol": "00929.TW",
      "name": "復華台灣科技優息",
      "price": 29.68,
      "change": 1.18,
      "pct": 4.14,
      "date": "06/12",
      "nav": 28.22,
      "premium": 0.99
    },
    {
      "symbol": "00940.TW",
      "name": "元大台灣價值高息",
      "price": 12.28,
      "change": 0.22,
      "pct": 1.82,
      "date": "06/12",
      "nav": 12.08,
      "premium": -0.17
    },
    {
      "symbol": "00403A.TW",
      "name": "統一台股升級50",
      "price": 10.3,
      "change": 0.31,
      "pct": 3.1,
      "date": "06/12",
      "nav": 10.02,
      "premium": -0.3
    },
    {
      "symbol": "00988A.TW",
      "name": "主動統一全球創新",
      "price": 20.91,
      "change": 1.06,
      "pct": 5.34,
      "date": "06/12",
      "nav": 20.66,
      "premium": -3.92
    },
    {
      "symbol": "00981A.TW",
      "name": "主動統一台股增長",
      "price": 30.72,
      "change": 1.01,
      "pct": 3.4,
      "date": "06/12",
      "nav": 29.78,
      "premium": -0.24
    },
    {
      "symbol": "00935.TW",
      "name": "野村臺灣新科技50",
      "price": 59.15,
      "change": 2.25,
      "pct": 3.95,
      "date": "06/12",
      "nav": 56.96,
      "premium": -0.11
    },
    {
      "symbol": "00980A.TW",
      "name": "主動野村臺灣優選",
      "price": 23.98,
      "change": 0.7,
      "pct": 3.01,
      "date": "06/12",
      "nav": 23.45,
      "premium": -0.72
    },
    {
      "symbol": "00631L.TW",
      "name": "元大台灣50正2",
      "price": 34.99,
      "change": 1.76,
      "pct": 5.3,
      "date": "06/12",
      "nav": 33.46,
      "premium": -0.69
    },
    {
      "symbol": "00675L.TW",
      "name": "富邦台灣加權正2",
      "price": 308.95,
      "change": 16.35,
      "pct": 5.59,
      "date": "06/12",
      "nav": 295.36,
      "premium": -0.93
    },
    {
      "symbol": "00663L.TW",
      "name": "國泰臺灣加權正2",
      "price": 102.05,
      "change": 5.4,
      "pct": 5.59,
      "date": "06/12",
      "nav": 97.56,
      "premium": -0.93
    }
  ]
}