{
  "updated": "2026/05/12 10:10",
  "twii": {
    "name": "台股大盤",
    "symbol": "^TWII",
    "price": 41680.43,
    "change": -109.63,
    "pct": -0.26,
    "date": "05/12",
    "ma5": 41629.41,
    "ma20": 39151.68,
    "ma120": 32206.32,
    "bias5": 0.12,
    "bias20": 6.46,
    "bias120": 29.42,
    "vol3": [
      15240.1,
      12469.0,
      13053.9
    ],
    "vol_ma5": 12353.9,
    "vol_ma20": 10237.7,
    "vol_ma120": 7447.9
  },
  "etf0050": {
    "name": "0050 元大台灣50",
    "symbol": "0050.TW",
    "price": 96.0,
    "change": -0.9,
    "pct": -0.93,
    "date": "05/12",
    "ma5": 96.67,
    "ma20": 90.42,
    "ma120": 73.01,
    "bias5": -0.69,
    "bias20": 6.17,
    "bias120": 31.49,
    "vol3": [
      117640,
      88545,
      47056
    ],
    "vol_ma5": 93807,
    "vol_ma20": 103108,
    "vol_ma120": 115578,
    "vol3_amt": [
      114.1,
      85.8,
      45.2
    ],
    "vol_ma5_amt": 90.8,
    "vol_ma20_amt": 93.2,
    "vol_ma120_amt": 85.0
  }
}