{
  "updated": "2026/07/15 13:10",
  "futures": [
    {
      "symbol": "TX",
      "name": "台指期",
      "price": 46149.0,
      "change": 1004.0,
      "pct": 2.22,
      "change_open": -434.0,
      "pct_open": -0.93,
      "contract": "202608",
      "date": "07/15"
    },
    {
      "symbol": "MTX",
      "name": "小台",
      "price": 46149.0,
      "change": 1004.0,
      "pct": 2.22,
      "change_open": -232.0,
      "pct_open": -0.5,
      "contract": "202608",
      "date": "07/15"
    },
    {
      "symbol": "TMF",
      "name": "微台",
      "price": 46149.0,
      "change": 1004.0,
      "pct": 2.22,
      "change_open": -421.0,
      "pct_open": -0.91,
      "contract": "202608",
      "date": "07/15"
    },
    {
      "symbol": "TE",
      "name": "電子期",
      "price": 46146.0,
      "change": 1001.0,
      "pct": 2.22,
      "change_open": -21.0,
      "pct_open": -0.7,
      "contract": "202608",
      "date": "07/15"
    }
  ]
}